LICENSE.txt
MANIFEST.in
README.md
setup.py
cmsplugin_forms_builder/__init__.py
cmsplugin_forms_builder/cms_plugins.py
cmsplugin_forms_builder/models.py
cmsplugin_forms_builder/tests.py
cmsplugin_forms_builder.egg-info/PKG-INFO
cmsplugin_forms_builder.egg-info/SOURCES.txt
cmsplugin_forms_builder.egg-info/dependency_links.txt
cmsplugin_forms_builder.egg-info/not-zip-safe
cmsplugin_forms_builder.egg-info/requires.txt
cmsplugin_forms_builder.egg-info/top_level.txt
cmsplugin_forms_builder/migrations/0001_initial.py
cmsplugin_forms_builder/migrations/0002_update_related_name.py
cmsplugin_forms_builder/migrations/__init__.py
cmsplugin_forms_builder/south_migrations/0001_initial.py
cmsplugin_forms_builder/south_migrations/__init__.py