Metadata-Version: 1.1
Name: cmsplugin-forms-builder
Version: 1.1.1
Summary: django-cms plugin for cmsplugin-forms-builder
Home-page: https://github.com/nimbis/cmsplugin-forms-builder/
Author: Nimbis Services, Inc.
Author-email: devops@nimbisservices.com
License: BSD
Platform: UNKNOWN
Classifier: Development Status :: 4 - Beta
Classifier: Environment :: Web Environment
Classifier: Intended Audience :: Developers
Classifier: License :: OSI Approved :: BSD License
Classifier: Operating System :: OS Independent
Classifier: Programming Language :: Python
Classifier: Framework :: Django
